npaws/__init__.py
npaws/client.py
npaws/config.py
npaws/services/__init__.py
npaws/services/batch.py
npaws/services/ecs.py
npaws/services/rds.py
npaws/services/s3.py
npaws/services/sqs.py
npaws-0.1.46.dist-info/LICENSE
npaws-0.1.46.dist-info/METADATA
npaws-0.1.46.dist-info/WHEEL
npaws-0.1.46.dist-info/top_level.txt
npaws-0.1.46.dist-info/RECORD
